gopipexample/__init__.py
gopipexample/gopipexample.py
gopipexample-0.1.0.dist-info/DESCRIPTION.rst
gopipexample-0.1.0.dist-info/METADATA
gopipexample-0.1.0.dist-info/RECORD
gopipexample-0.1.0.dist-info/WHEEL
gopipexample-0.1.0.dist-info/metadata.json
gopipexample-0.1.0.dist-info/top_level.txt
