Metadata-Version: 2.0
Name: gopipexample
Version: 0.1.0
Summary: Simple example showing packaging of go binaries in pip
Home-page: https://github.com/robc-io/gopipexample
Author: robc-io
Author-email: robc.io.opensouce@gmail.com
License: Apache Software License 2.0
Keywords: gopipexample
Platform: UNKNOWN
Classifier: Development Status :: 2 - Pre-Alpha
Classifier: Intended Audience :: Developers
Classifier: License :: OSI Approved :: Apache Software License
Classifier: Natural Language :: English
Classifier: Programming Language :: Python :: 2
Classifier: Programming Language :: Python :: 2.7
Classifier: Programming Language :: Python :: 3
Classifier: Programming Language :: Python :: 3.4
Classifier: Programming Language :: Python :: 3.5
Classifier: Programming Language :: Python :: 3.6
Classifier: Programming Language :: Python :: 3.7
